CHANGES
MANIFEST.in
README.rst
setup.py
stdeb.cfg
yay/__init__.py
yay/composer.py
yay/config.py
yay/errors.py
yay/loader.py
yay/parser.py
yay/protectedstring.py
yay/pyparsing.py
yay/stringbuilder.py
yay.egg-info/PKG-INFO
yay.egg-info/SOURCES.txt
yay.egg-info/dependency_links.txt
yay.egg-info/not-zip-safe
yay.egg-info/requires.txt
yay.egg-info/top_level.txt
yay/doctests/__init__.py
yay/doctests/actions.rst
yay/doctests/extends.rst
yay/doctests/test_documentation.py
yay/nodes/__init__.py
yay/nodes/append.py
yay/nodes/boxed.py
yay/nodes/call.py
yay/nodes/context.py
yay/nodes/copy.py
yay/nodes/expression.py
yay/nodes/filter.py
yay/nodes/flatten.py
yay/nodes/foreach.py
yay/nodes/function.py
yay/nodes/mapping.py
yay/nodes/node.py
yay/nodes/remove.py
yay/nodes/secret.py
yay/nodes/select.py
yay/nodes/sequence.py
yay/nodes/undefined.py
yay/nodes/with_.py
yay/nodes/datastore/__init__.py
yay/nodes/datastore/bind.py
yay/nodes/datastore/dj.py
yay/nodes/datastore/sqlalch.py
yay/openers/__init__.py
yay/openers/base.py
yay/openers/package.py
yay/tests/__init__.py
yay/tests/test_bind_python.py
yay/tests/test_boxed.py
yay/tests/test_chaosmonkey.py
yay/tests/test_config.py
yay/tests/test_config_update.py
yay/tests/test_datastore_alch.py
yay/tests/test_datastore_alch_pymodel.py
yay/tests/test_dj.py
yay/tests/test_dogfood.py
yay/tests/test_errors.py
yay/tests/test_nodes.py
yay/tests/test_nodes_expressions.py
yay/tests/test_openers.py
yay/tests/test_parse_expressions.py
yay/tests/test_protectedstring.py
yay/tests/dj/__init__.py
yay/tests/dj/models.py
yay/tests/dj/settings.py
yay/tests/dogfood/append_empty.in
yay/tests/dogfood/append_empty.out
yay/tests/dogfood/config.in
yay/tests/dogfood/config.out
yay/tests/dogfood/copy_then_change_base_in_overly.base
yay/tests/dogfood/copy_then_change_base_in_overly.in
yay/tests/dogfood/copy_then_change_base_in_overly.out
yay/tests/dogfood/else.in
yay/tests/dogfood/else.out
yay/tests/dogfood/else_include.in
yay/tests/dogfood/else_include.out
yay/tests/dogfood/else_include_in.inc
yay/tests/dogfood/elseemptydict.in
yay/tests/dogfood/elseemptydict.out
yay/tests/dogfood/elseemptylist.in
