Metadata-Version: 1.0
Name: yay
Version: 0.0.62
Summary: An extensible config file format
Home-page: http://pypi.python.org/pypi/yay
Author: John Carr
Author-email: john.carr@isotoma.com
License: Apache Software License
Platform: UNKNOWN
Classifier: Development Status :: 3 - Alpha
Classifier: Intended Audience :: Developers
Classifier: License :: OSI Approved :: Apache Software License
Classifier: Operating System :: OS Independent
Classifier: Programming Language :: Python
Classifier: Topic :: System :: Systems Administration
